fbrp/__init__.py
fbrp/life_cycle.py
fbrp/process_def.py
fbrp/util.py
fbrp/cmd/__init__.py
fbrp/cmd/_autocomplete.py
fbrp/cmd/down.py
fbrp/cmd/info.py
fbrp/cmd/logs.py
fbrp/cmd/ps.py
fbrp/cmd/up.py
fbrp/cmd/wait.py
fbrp/runtime/__init__.py
fbrp/runtime/base.py
fbrp/runtime/conda.py
fbrp/runtime/docker.py
fbrp/runtime/host.py
fbrp/tool/__init__.py
fbrp-0.1.5.dist-info/METADATA
fbrp-0.1.5.dist-info/WHEEL
fbrp-0.1.5.dist-info/entry_points.txt
fbrp-0.1.5.dist-info/top_level.txt
fbrp-0.1.5.dist-info/RECORD
